pywcmp/__init__.py
pywcmp/bundle.py
pywcmp/errors.py
pywcmp/ets.py
pywcmp/kpi.py
pywcmp/pygeoapi_plugin.py
pywcmp/util.py
pywcmp/resources/dictionary.txt
pywcmp/resources/ets-report.json
pywcmp/resources/example-ca-eccc-msc.nwp-gdps.json
pywcmp/resources/kpi-report.json
pywcmp/wcmp2/__init__.py
pywcmp/wcmp2/ets.py
pywcmp/wcmp2/kpi.py
pywcmp-0.12.4.dist-info/licenses/LICENSE.md
pywcmp-0.12.4.dist-info/METADATA
pywcmp-0.12.4.dist-info/WHEEL
pywcmp-0.12.4.dist-info/entry_points.txt
pywcmp-0.12.4.dist-info/top_level.txt
pywcmp-0.12.4.dist-info/RECORD
