Metadata-Version: 2.4
Name: pywcmp
Version: 0.12.4
Summary: A Python implementation of the test suite for WMO Core Metadata Profile
Home-page: https://github.com/World-Meteorological-Organization/pywcmp
Author: Tom Kralidis
Author-email: tomkralidis@gmail.com
Maintainer: Tom Kralidis
Maintainer-email: tomkralidis@gmail.com
License: Apache Software License
Keywords: WMO Metadata WIS Test Suite
Platform: all
Classifier: Development Status :: 4 - Beta
Classifier: Environment :: Console
Classifier: Intended Audience :: Developers
Classifier: Intended Audience :: Science/Research
Classifier: License :: OSI Approved :: Apache Software License
Classifier: Operating System :: OS Independent
Classifier: Programming Language :: Python
Classifier: Topic :: Scientific/Engineering :: Atmospheric Science
Classifier: Topic :: Scientific/Engineering :: GIS
License-File: LICENSE.md
Requires-Dist: beautifulsoup4
Requires-Dist: click
Requires-Dist: jsonschema
Requires-Dist: pyspellchecker
Requires-Dist: pywis-topics
Requires-Dist: rfc3339-validator
Requires-Dist: rfc3987
Requires-Dist: shapely
Dynamic: author
Dynamic: author-email
Dynamic: classifier
Dynamic: description
Dynamic: description-content-type
Dynamic: home-page
Dynamic: keywords
Dynamic: license
Dynamic: license-file
Dynamic: maintainer
Dynamic: maintainer-email
Dynamic: platform
Dynamic: requires-dist
Dynamic: summary
